maggma/__init__.py
maggma/py.typed
maggma/utils.py
maggma/validators.py
maggma/api/API.py
maggma/api/__init__.py
maggma/api/default_responses.yaml
maggma/api/models.py
maggma/api/utils.py
maggma/api/query_operator/__init__.py
maggma/api/query_operator/core.py
maggma/api/query_operator/dynamic.py
maggma/api/query_operator/pagination.py
maggma/api/query_operator/sorting.py
maggma/api/query_operator/sparse_fields.py
maggma/api/query_operator/submission.py
maggma/api/resource/__init__.py
maggma/api/resource/aggregation.py
maggma/api/resource/core.py
maggma/api/resource/post_resource.py
maggma/api/resource/read_resource.py
maggma/api/resource/s3_url.py
maggma/api/resource/submission.py
maggma/api/resource/utils.py
maggma/builders/__init__.py
maggma/builders/group_builder.py
maggma/builders/map_builder.py
maggma/builders/projection_builder.py
maggma/cli/__init__.py
maggma/cli/distributed.py
maggma/cli/multiprocessing.py
maggma/cli/rabbitmq.py
maggma/cli/serial.py
maggma/cli/settings.py
maggma/cli/source_loader.py
maggma/cli/sources/__init__.py
maggma/core/__init__.py
maggma/core/builder.py
maggma/core/store.py
maggma/core/validator.py
maggma/stores/__init__.py
maggma/stores/advanced_stores.py
maggma/stores/aws.py
maggma/stores/azure.py
maggma/stores/compound_stores.py
maggma/stores/file_store.py
maggma/stores/gridfs.py
maggma/stores/mongolike.py
maggma/stores/open_data.py
maggma/stores/shared_stores.py
maggma/stores/ssh_tunnel.py
maggma-0.72.0.dist-info/licenses/LICENSE
maggma-0.72.0.dist-info/METADATA
maggma-0.72.0.dist-info/WHEEL
maggma-0.72.0.dist-info/entry_points.txt
maggma-0.72.0.dist-info/top_level.txt
maggma-0.72.0.dist-info/RECORD
